tamper_framework/__init__.py
tamper_framework/__version__.py
tamper_framework/ast_builder.py
tamper_framework/ast_transformer.py
tamper_framework/context.py
tamper_framework/lexer.py
tamper_framework/transformer.py
tamper_framework/transformations/__init__.py
tamper_framework/transformations/case_alternate.py
tamper_framework/transformations/keyword_wrap.py
tamper_framework/transformations/space_replace.py
tamper_framework/transformations/value_encode.py
sqlmap_tamper_framework-2.0.1.dist-info/METADATA
sqlmap_tamper_framework-2.0.1.dist-info/WHEEL
sqlmap_tamper_framework-2.0.1.dist-info/top_level.txt
sqlmap_tamper_framework-2.0.1.dist-info/RECORD
